anemoi/utils/__init__.py
anemoi/utils/__main__.py
anemoi/utils/_environment.py
anemoi/utils/_version.py
anemoi/utils/caching.py
anemoi/utils/checkpoints.py
anemoi/utils/cli.py
anemoi/utils/compatibility.py
anemoi/utils/config.py
anemoi/utils/dates.py
anemoi/utils/devtools.py
anemoi/utils/grib.py
anemoi/utils/grids.py
anemoi/utils/hindcasts.py
anemoi/utils/humanize.py
anemoi/utils/logs.py
anemoi/utils/provenance.py
anemoi/utils/registry.py
anemoi/utils/rules.py
anemoi/utils/s3.py
anemoi/utils/sanitise.py
anemoi/utils/sanitize.py
anemoi/utils/testing.py
anemoi/utils/text.py
anemoi/utils/timer.py
anemoi/utils/commands/__init__.py
anemoi/utils/commands/config.py
anemoi/utils/commands/metadata.py
anemoi/utils/commands/requests.py
anemoi/utils/commands/transfer.py
anemoi/utils/mars/__init__.py
anemoi/utils/mars/mars.yaml
anemoi/utils/mars/requests.py
anemoi/utils/mlflow/__init__.py
anemoi/utils/mlflow/auth.py
anemoi/utils/mlflow/client.py
anemoi/utils/mlflow/utils.py
anemoi/utils/remote/__init__.py
anemoi/utils/remote/s3.py
anemoi/utils/remote/ssh.py
anemoi/utils/schemas/__init__.py
anemoi/utils/schemas/errors.py
anemoi_utils-0.4.43.dist-info/licenses/LICENSE
anemoi_utils-0.4.43.dist-info/METADATA
anemoi_utils-0.4.43.dist-info/WHEEL
anemoi_utils-0.4.43.dist-info/entry_points.txt
anemoi_utils-0.4.43.dist-info/top_level.txt
anemoi_utils-0.4.43.dist-info/RECORD
