Metadata-Version: 2.4
Name: anemoi-utils
Version: 0.4.43
Summary: A package to hold various functions to support training of ML models on ECMWF data.
Author-email: "European Centre for Medium-Range Weather Forecasts (ECMWF)" <software.support@ecmwf.int>
License:                                  Apache License
Project-URL: Documentation, https://anemoi-utils.readthedocs.io/
Project-URL: Homepage, https://github.com/ecmwf/anemoi-utils/
Project-URL: Issues, https://github.com/ecmwf/anemoi-utils/issues
Project-URL: Repository, https://github.com/ecmwf/anemoi-utils/
Keywords: ai,tools
Classifier: Development Status :: 4 - Beta
Classifier: Intended Audience :: Developers
Classifier: License :: OSI Approved :: Apache Software License
Classifier: Operating System :: OS Independent
Classifier: Programming Language :: Python :: 3 :: Only
Classifier: Programming Language :: Python :: 3.10
Classifier: Programming Language :: Python :: 3.11
Classifier: Programming Language :: Python :: 3.12
Classifier: Programming Language :: Python :: Implementation :: CPython
Classifier: Programming Language :: Python :: Implementation :: PyPy
Requires-Python: >=3.10
License-File: LICENSE
Requires-Dist: aniso8601
Requires-Dist: deprecation
Requires-Dist: entrypoints
Requires-Dist: importlib-metadata; python_version < "3.10"
Requires-Dist: multiurl
Requires-Dist: numpy
Requires-Dist: pydantic>=2.9
Requires-Dist: python-dateutil
Requires-Dist: pyyaml
Requires-Dist: rich
Requires-Dist: tomli; python_version < "3.11"
Requires-Dist: tqdm
Provides-Extra: all
Requires-Dist: anemoi-utils[grib,mlflow,provenance,s3,text]; extra == "all"
Provides-Extra: dev
Requires-Dist: anemoi-utils[all,docs,tests]; extra == "dev"
Provides-Extra: docs
Requires-Dist: anemoi-utils[all]; extra == "docs"
Requires-Dist: nbsphinx; extra == "docs"
Requires-Dist: pandoc; extra == "docs"
Requires-Dist: requests; extra == "docs"
Requires-Dist: sphinx; extra == "docs"
Requires-Dist: sphinx-argparse; extra == "docs"
Requires-Dist: sphinx-rtd-theme; extra == "docs"
Requires-Dist: termcolor; extra == "docs"
Provides-Extra: grib
Requires-Dist: requests; extra == "grib"
Provides-Extra: mlflow
Requires-Dist: mlflow-skinny>=2.11.1; extra == "mlflow"
Requires-Dist: requests; extra == "mlflow"
Provides-Extra: provenance
Requires-Dist: gitpython; extra == "provenance"
Requires-Dist: nvsmi; extra == "provenance"
Provides-Extra: s3
Requires-Dist: obstore; extra == "s3"
Provides-Extra: tests
Requires-Dist: anemoi-utils[mlflow]; extra == "tests"
Requires-Dist: pytest; extra == "tests"
Requires-Dist: pytest-mock>=3; extra == "tests"
Provides-Extra: text
Requires-Dist: termcolor; extra == "text"
Requires-Dist: wcwidth; extra == "text"
Dynamic: license-file
